rtl/global.v
`ifndef __GLOBAL_H__
`define __GLOBAL_H__

// 以下都为正逻辑，负逻辑在后面加_
// 正逻辑
`define RESET 1'b0
`define A_PC 32'd4
`define WORD_ADDR 31:0
`define WORD_DATA 31:0

`define ENABLE 1'b1
`define DISABLE 1'b0

`define DEFAULT_32_ZERO 32'b0
`define DEFAULT_5_ZERO 5'b0

`define RISCV_OPCODE 6:0
`define RISCV_RD 4:0
`define RISCV_RS1 4:0
`define RISCV_RS2 4:0
`define RISCV_FUNCT3 2:0

`define RISCV_IMMI 11:0
`define RISCV_IMMSB 12:0
`define RISCV_IMMUJ 20:0
// 此处改成32位，前面没考虑周到
// `define RISCV_IMMI 31:0
// `define RISCV_IMMSB 31:0
// `define RISCV_IMMUJ 31:0

`define REGS_ADDR 4:0
`define REGS_NUM 6'd32 // ?

// 总线
`define BUS_OWNER_MASTER_0 2'b00
`define BUS_OWNER_MASTER_1 2'b01
`define BUS_OWNER_MASTER_2 2'b10
`define BUS_OWNER_MASTER_3 2'b11

`define BUS_SLAVE_0 3'b000
`define BUS_SLAVE_1 3'b001
`define BUS_SLAVE_2 3'b010
`define BUS_SLAVE_3 3'b011
`define BUS_SLAVE_4 3'b100
`define BUS_SLAVE_5 3'b101
`define BUS_SLAVE_6 3'b110
`define BUS_SLAVE_7 3'b111

// 读写
`define READ 1'b0
`define WRITE 1'b1

`define BUS_SLAVE_ADDR 2:0 // 参考了《CPU自制入门一书》，书中相关的值给了30，这里给了3我觉得就够了

// 负逻辑

`endif

rtl/Timer.v
`include "global.v"

// 若切换模式则需要复位一次
module Timer(
    input wire clk,
    input wire rest,
    // Bus Interface
    input  wire Timer_cs,                  // 片选
    input  wire Timer_as,                  // 选通
    input  wire Timer_rw,                  // 读写
    output reg Timer_rdy,                  // 就绪
    input wire[2:0] Timer_addr,            // 地址
    input wire[`WORD_DATA] Timer_wr_data,  // 写数据
    output reg[`WORD_DATA] Timer_rd_data,  // 读数据
    output reg Timer_irq                   // 中断
);
    // 暂时只支持向上计数
    // reg expr_flag = (counter == expr_val) && (start == `TIMER_ENABLE) ? `ENABLE : `DISABLE;
    reg expr_flag;
    // 模式选择
    // 高位决定向上/向下计数，低位决定单次/循环计数
    reg[1:0] mode;
    reg start; // 开始位
    // `WORD_DATA决定了最大的计数值
    reg[`WORD_DATA] expr_val; // 最大值
    reg[`WORD_DATA] counter; // 计数器

    always @(*) begin
        Timer_irq = expr_flag; // 计数器满则下一个周期发起中断
        if (start == `TIMER_ENABLE) begin // 开始计时
            case(mode[0])
                `TIMER_UP:begin
                    if (counter == expr_val) begin
                        expr_flag = `ENABLE;
                    end else begin
                        expr_flag = `DISABLE;
                    end
                end
                `TIMER_DOWN:begin
                    if (counter == 32'b0) begin
                        expr_flag = `ENABLE;
                    end else begin
                        expr_flag = `DISABLE;
                    end
                end
                default:begin
                    expr_flag = `DISABLE;
                end
            endcase
        end else begin
            expr_flag = `DISABLE;
        end
        
    end

    always @(posedge clk) begin

        if (rest == `RESET) begin
            mode <= `TIMER_MODE_SINGLE_UP;
            start <= `TIMER_DISABLE;
            expr_val <= `TIMER_MAX_EXPR;
        end else begin
            // 就绪
            if ((Timer_cs == `ENABLE) && (Timer_as == `ENABLE)) begin
                Timer_rdy <= `ENABLE;
            end else begin
                Timer_rdy <= `DISABLE;
            end

            // 读出控制
            if ((Timer_cs == `ENABLE) && (Timer_as == `ENABLE) && (Timer_rw == `READ)) begin               
                case (Timer_addr)
                    `TIMER_EXPR_ADDR:begin
                        Timer_rd_data <= expr_val;
                    end
                    `TIMER_COUNTER_ADDR:begin
                        Timer_rd_data <= counter;
                    end
                    `TIMER_STATE_ADDR:begin
                        Timer_rd_data <= {{29{1'b0}}, mode, start};
                    end
                endcase
            end
            // 写入控制
            if ((Timer_cs == `ENABLE) && (Timer_as == `ENABLE) &&
                (Timer_rw == `WRITE) && (Timer_addr == `TIMER_CTRL_ADDR)) begin
                mode <= Timer_wr_data[1:0];
                start <= Timer_wr_data[2];
            end

            // 更新计数器
            if (expr_flag == `ENABLE)begin // 计数器满
                case(mode)
                    `TIMER_MODE_SINGLE_UP,`TIMER_MODE_SINGLE_DOWN:begin // 单次计数
                        start <= `TIMER_DISABLE;
                    end
                    `TIMER_MODE_CIRCLE_UP:begin // 循环计数
                        counter <= 32'b0;
                    end
                    `TIMER_MODE_CIRCLE_DOWN:begin
                        counter <= expr_val;
                    end
                endcase
            end else if (start == `TIMER_ENABLE)begin
                case (mode[0])
                    `TIMER_UP:begin // 向上计数
                        counter <= counter + 32'b1;
                    end
                    `TIMER_DOWN:begin // 向下计数
                        counter <= counter - 32'b1;
                    end
                endcase
            end else begin // start位置停止的计数器清零
                counter <= 32'b0;
            end
        end
        
    end

endmodule

tb/module_tb.v
`timescale 1ns/1ns
`include "global.v"

module module_tb;

    reg clk;
    reg rest;
    reg cs;
    reg as;
    reg rw;
    wire rdy;
    reg[2:0] addr;
    reg[`WORD_DATA] wr_data;
    wire[`WORD_DATA] rd_data;
    wire irq;

    initial begin
        clk = 0;
		rest <= 1'b0;
		#10;
		rest <= 1'b1;
        #10;
        cs <= `ENABLE;
        as <= `ENABLE;
        rw <= `WRITE;
        addr <= `TIMER_CTRL_ADDR;
        // 向上计数
        wr_data <= `TIMER_CIRCLE_UP;
        #3000
        // 向下计数
        wr_data <= `TIMER_CIRCLE_DOWN;
        // 暂停
        #500;
        wr_data <= `TIMER_STOP;
    end

    always #10 clk = ~clk;

    initial begin
        forever begin
			@(posedge clk) 
			$display("counter register value is %d",module_tb.u_Timer.counter);
			$display("expr_val register value is %d",module_tb.u_Timer.expr_val);
			$display("expr_flag register value is %d",module_tb.u_Timer.expr_flag);
			$display("---------------------------");
			$display("---------------------------");
		end
    end

    initial begin
        $dumpfile("./generated/module_tb.vcd");
        $dumpvars(0, module_tb);
    end

    initial begin
        #20000;
        $finish;
    end

    Timer u_Timer(
        .clk           (clk     ),
        .rest          (rest    ),
        .Timer_cs      (cs      ),
        .Timer_as      (as      ),
        .Timer_rw      (rw      ),
        .Timer_rdy     (rdy     ),
        .Timer_addr    (addr    ),
        .Timer_wr_data (wr_data ),
        .Timer_rd_data (rd_data ),
        .Timer_irq     (irq     )
    );
endmodule

tb/generated/module_tb.vcd
$date
	Fri Mar 08 20:27:18 2024
$end
$version
	Icarus Verilog
$end
$timescale
	1ns
$end
$scope module module_tb $end
$var wire 1 ! rdy $end
$var wire 32 " rd_data [31:0] $end
$var wire 1 # irq $end
$var reg 3 $ addr [2:0] $end
$var reg 1 % as $end
$var reg 1 & clk $end
$var reg 1 ' cs $end
$var reg 1 ( rest $end
$var reg 1 ) rw $end
$var reg 32 * wr_data [31:0] $end
$scope module u_Timer $end
$var wire 3 + Timer_addr [2:0] $end
$var wire 1 % Timer_as $end
$var wire 1 ' Timer_cs $end
$var wire 1 ) Timer_rw $end
$var wire 32 , Timer_wr_data [31:0] $end
$var wire 1 & clk $end
$var wire 1 ( rest $end
$var reg 1 # Timer_irq $end
$var reg 32 - Timer_rd_data [31:0] $end
$var reg 1 ! Timer_rdy $end
$var reg 32 . counter [31:0] $end
$var reg 1 / expr_flag $end
$var reg 32 0 expr_val [31:0] $end
$var reg 2 1 mode [1:0] $end
$var reg 1 2 start $end
$upscope $end
$upscope $end
$enddefinitions $end
$comment Show the parameter values. $end
$dumpall
$end
#0
$dumpvars
x2
bx 1
bx 0
x/
bx .
bx -
bx ,
bx +
bx *
x)
0(
x'
0&
x%
bx $
x#
bx "
x!
$end
#10
0/
b11111111 0
12
b11 1
1(
1&
#20
b1 *
b1 ,
b11 $
b11 +
1)
1%
1'
0&
#30
0#
b0 .
02
b1 1
1!
1&
#40
0&
#50
b1 .
1&
#60
0&
#70
b10 .
1&
#80
0&
#90
b11 .
1&
#100
0&
#110
b100 .
1&
#120
0&
#130
b101 .
1&
#140
0&
#150
b110 .
1&
#160
0&
#170
b111 .
1&
#180
0&
#190
b1000 .
1&
#200
0&
#210
b1001 .
1&
#220
0&
#230
b1010 .
1&
#240
0&
#250
b1011 .
1&
#260
0&
#270
b1100 .
1&
#280
0&
#290
b1101 .
1&
#300
0&
#310
b1110 .
1&
#320
0&
#330
b1111 .
1&
#340
0&
#350
b10000 .
1&
#360
0&
#370
b10001 .
1&
#380
0&
#390
b10010 .
1&
#400
0&
#410
b10011 .
1&
#420
0&
#430
b10100 .
1&
#440
0&
#450
b10101 .
1&
#460
0&
#470
b10110 .
1&
#480
0&
#490
b10111 .
1&
#500
0&
#510
b11000 .
1&
#520
0&
#530
b11001 .
1&
#540
0&
#550
b11010 .
1&
#560
0&
#570
b11011 .
1&
#580
0&
#590
b11100 .
1&
#600
0&
#610
b11101 .
1&
#620
0&
#630
b11110 .
1&
#640
0&
#650
b11111 .
1&
#660
0&
#670
b100000 .
1&
#680
0&
#690
b100001 .
1&
#700
0&
#710
b100010 .
1&
#720
0&
#730
b100011 .
1&
#740
0&
#750
b100100 .
1&
#760
0&
#770
b100101 .
1&
#780
0&
#790
b100110 .
1&
#800
0&
#810
b100111 .
1&
#820
0&
#830
b101000 .
1&
#840
0&
#850
b101001 .
1&
#860
0&
#870
b101010 .
1&
#880
0&
#890
b101011 .
1&
#900
0&
#910
b101100 .
1&
#920
0&
#930
b101101 .
1&
#940
0&
#950
b101110 .
1&
#960
0&
#970
b101111 .
1&
#980
0&
#990
b110000 .
1&
#1000
0&
#1010
b110001 .
1&
#1020
0&
#1030
b110010 .
1&
#1040
0&
#1050
b110011 .
1&
#1060
0&
#1070
b110100 .
1&
#1080
0&
#1090
b110101 .
1&
#1100
0&
#1110
b110110 .
1&
#1120
0&
#1130
b110111 .
1&
#1140
0&
#1150
b111000 .
1&
#1160
0&
#1170
b111001 .
1&
#1180
0&
#1190
b111010 .
1&
#1200
0&
#1210
b111011 .
1&
#1220
0&
#1230
b111100 .
1&
#1240
0&
#1250
b111101 .
1&
#1260
0&
#1270
b111110 .
1&
#1280
0&
#1290
b111111 .
1&
#1300
0&
#1310
b1000000 .
1&
#1320
0&
#1330
b1000001 .
1&
#1340
0&
#1350
b1000010 .
1&
#1360
0&
#1370
b1000011 .
1&
#1380
0&
#1390
b1000100 .
1&
#1400
0&
#1410
b1000101 .
1&
#1420
0&
#1430
b1000110 .
1&
#1440
0&
#1450
b1000111 .
1&
#1460
0&
#1470
b1001000 .
1&
#1480
0&
#1490
b1001001 .
1&
#1500
0&
#1510
b1001010 .
1&
#1520
0&
#1530
b1001011 .
1&
#1540
0&
#1550
b1001100 .
1&
#1560
0&
#1570
b1001101 .
1&
#1580
0&
#1590
b1001110 .
1&
#1600
0&
#1610
b1001111 .
1&
#1620
0&
#1630
b1010000 .
1&
#1640
0&
#1650
b1010001 .
1&
#1660
0&
#1670
b1010010 .
1&
#1680
0&
#1690
b1010011 .
1&
#1700
0&
#1710
b1010100 .
1&
#1720
0&
#1730
b1010101 .
1&
#1740
0&
#1750
b1010110 .
1&
#1760
0&
#1770
b1010111 .
1&
#1780
0&
#1790
b1011000 .
1&
#1800
0&
#1810
b1011001 .
1&
#1820
0&
#1830
b1011010 .
1&
#1840
0&
#1850
b1011011 .
1&
#1860
0&
#1870
b1011100 .
1&
#1880
0&
#1890
b1011101 .
1&
#1900
0&
#1910
b1011110 .
1&
#1920
0&
#1930
b1011111 .
1&
#1940
0&
#1950
b1100000 .
1&
#1960
0&
#1970
b1100001 .
1&
#1980
0&
#1990
b1100010 .
1&
#2000
0&
#2010
b1100011 .
1&
#2020
0&
#2030
b1100100 .
1&
#2040
0&
#2050
b1100101 .
1&
#2060
0&
#2070
b1100110 .
1&
#2080
0&
#2090
b1100111 .
1&
#2100
0&
#2110
b1101000 .
1&
#2120
0&
#2130
b1101001 .
1&
#2140
0&
#2150
b1101010 .
1&
#2160
0&
#2170
b1101011 .
1&
#2180
0&
#2190
b1101100 .
1&
#2200
0&
#2210
b1101101 .
1&
#2220
0&
#2230
b1101110 .
1&
#2240
0&
#2250
b1101111 .
1&
#2260
0&
#2270
b1110000 .
1&
#2280
0&
#2290
b1110001 .
1&
#2300
0&
#2310
b1110010 .
1&
#2320
0&
#2330
b1110011 .
1&
#2340
0&
#2350
b1110100 .
1&
#2360
0&
#2370
b1110101 .
1&
#2380
0&
#2390
b1110110 .
1&
#2400
0&
#2410
b1110111 .
1&
#2420
0&
#2430
b1111000 .
1&
#2440
0&
#2450
b1111001 .
1&
#2460
0&
#2470
b1111010 .
1&
#2480
0&
#2490
b1111011 .
1&
#2500
0&
#2510
b1111100 .
1&
#2520
0&
#2530
b1111101 .
1&
#2540
0&
#2550
b1111110 .
1&
#2560
0&
#2570
b1111111 .
1&
#2580
0&
#2590
b10000000 .
1&
#2600
0&
#2610
b10000001 .
1&
#2620
0&
#2630
b10000010 .
1&
#2640
0&
#2650
b10000011 .
1&
#2660
0&
#2670
b10000100 .
1&
#2680
0&
#2690
b10000101 .
1&
#2700
0&
#2710
b10000110 .
1&
#2720
0&
#2730
b10000111 .
1&
#2740
0&
#2750
b10001000 .
1&
#2760
0&
#2770
b10001001 .
1&
#2780
0&
#2790
b10001010 .
1&
#2800
0&
#2810
b10001011 .
1&
#2820
0&
#2830
b10001100 .
1&
#2840
0&
#2850
b10001101 .
1&
#2860
0&
#2870
b10001110 .
1&
#2880
0&
#2890
b10001111 .
1&
#2900
0&
#2910
b10010000 .
1&
#2920
0&
#2930
b10010001 .
1&
#2940
0&
#2950
b10010010 .
1&
#2960
0&
#2970
b10010011 .
1&
#2980
0&
#2990
b10010100 .
1&
#3000
0&
#3010
b10010101 .
1&
#3020
b0 *
b0 ,
0&
#3030
b10010110 .
b0 1
1&
#3040
0&
#3050
b10010101 .
1&
#3060
0&
#3070
b10010100 .
1&
#3080
0&
#3090
b10010011 .
1&
#3100
0&
#3110
b10010010 .
1&
#3120
0&
#3130
b10010001 .
1&
#3140
0&
#3150
b10010000 .
1&
#3160
0&
#3170
b10001111 .
1&
#3180
0&
#3190
b10001110 .
1&
#3200
0&
#3210
b10001101 .
1&
#3220
0&
#3230
b10001100 .
1&
#3240
0&
#3250
b10001011 .
1&
#3260
0&
#3270
b10001010 .
1&
#3280
0&
#3290
b10001001 .
1&
#3300
0&
#3310
b10001000 .
1&
#3320
0&
#3330
b10000111 .
1&
#3340
0&
#3350
b10000110 .
1&
#3360
0&
#3370
b10000101 .
1&
#3380
0&
#3390
b10000100 .
1&
#3400
0&
#3410
b10000011 .
1&
#3420
0&
#3430
b10000010 .
1&
#3440
0&
#3450
b10000001 .
1&
#3460
0&
#3470
b10000000 .
1&
#3480
0&
#3490
b1111111 .
1&
#3500
0&
#3510
b1111110 .
1&
#3520
b100 *
b100 ,
0&
#3530
b1111101 .
12
1&
#3540
0&
#3550
b0 .
1&
